{
  "timestamp": "2026-03-01T15:57:09.163775+00:00",
  "n_species": 190,
  "n_unique_molecules": 135,
  "n_complete": 190,
  "n_partial": 0,
  "n_error": 0,
  "species": [
    {
      "molecule_id": "Al+_singlet_Kh",
      "basis": "sto-3g",
      "status": "complete",
      "n_alphas": 1,
      "n_ok": 1,
      "n_fci_converged": 1,
      "n_spin_mismatch": 0,
      "elapsed_s": 0,
      "error": null,
      "alphas": []
    },
    {
      "molecule_id": "Al-_singlet_Kh",
      "basis": "sto-3g",
      "status": "complete",
      "n_alphas": 1,
      "n_ok": 1,
      "n_fci_converged": 1,
      "n_spin_mismatch": 0,
      "elapsed_s": 0,
      "error": null,
      "alphas": []
    },
    {
      "molecule_id": "AlH2+_singlet_C2v",
      "basis": "sto-3g",
      "status": "complete",
      "n_alphas": 10,
      "n_ok": 10,
      "n_fci_converged": 10,
      "n_spin_mismatch": 0,
      "elapsed_s": 0,
      "error": null,
      "alphas": []
    },
    {
      "molecule_id": "AlH2-_singlet_C2v",
      "basis": "sto-3g",
      "status": "complete",
      "n_alphas": 10,
      "n_ok": 10,
      "n_fci_converged": 10,
      "n_spin_mismatch": 0,
      "elapsed_s": 0,
      "error": null,
      "alphas": []
    },
    {
      "molecule_id": "AlH3_singlet_D3h",
      "basis": "sto-3g",
      "status": "complete",
      "n_alphas": 10,
      "n_ok": 10,
      "n_fci_converged": 10,
      "n_spin_mismatch": 0,
      "elapsed_s": 0,
      "error": null,
      "alphas": []
    },
    {
      "molecule_id": "AlH_singlet_Coov",
      "basis": "sto-3g",
      "status": "complete",
      "n_alphas": 10,
      "n_ok": 10,
      "n_fci_converged": 10,
      "n_spin_mismatch": 0,
      "elapsed_s": 0,
      "error": null,
      "alphas": []
    },
    {
      "molecule_id": "ArH+_singlet_C1",
      "basis": "sto-3g",
      "status": "complete",
      "n_alphas": 10,
      "n_ok": 10,
      "n_fci_converged": 10,
      "n_spin_mismatch": 0,
      "elapsed_s": 0,
      "error": null,
      "alphas": []
    },
    {
      "molecule_id": "ArH2_singlet_Coov",
      "basis": "sto-3g",
      "status": "complete",
      "n_alphas": 10,
      "n_ok": 10,
      "n_fci_converged": 10,
      "n_spin_mismatch": 0,
      "elapsed_s": 0,
      "error": null,
      "alphas": []
    },
    {
      "molecule_id": "Ar_singlet_Kh",
      "basis": "sto-3g",
      "status": "complete",
      "n_alphas": 1,
      "n_ok": 1,
      "n_fci_converged": 1,
      "n_spin_mismatch": 0,
      "elapsed_s": 0,
      "error": null,
      "alphas": []
    },
    {
      "molecule_id": "B+_singlet_Kh",
      "basis": "3-21g",
      "status": "complete",
      "n_alphas": 1,
      "n_ok": 1,
      "n_fci_converged": 1,
      "n_spin_mismatch": 0,
      "elapsed_s": 0,
      "error": null,
      "alphas": []
    },
    {
      "molecule_id": "B+_singlet_Kh",
      "basis": "sto-3g",
      "status": "complete",
      "n_alphas": 1,
      "n_ok": 1,
      "n_fci_converged": 1,
      "n_spin_mismatch": 0,
      "elapsed_s": 0,
      "error": null,
      "alphas": []
    },
    {
      "molecule_id": "B2H2_singlet_Dooh",
      "basis": "sto-3g",
      "status": "complete",
      "n_alphas": 10,
      "n_ok": 10,
      "n_fci_converged": 10,
      "n_spin_mismatch": 0,
      "elapsed_s": 0,
      "error": null,
      "alphas": []
    },
    {
      "molecule_id": "BF_singlet_Coov",
      "basis": "sto-3g",
      "status": "complete",
      "n_alphas": 10,
      "n_ok": 10,
      "n_fci_converged": 10,
      "n_spin_mismatch": 0,
      "elapsed_s": 0,
      "error": null,
      "alphas": []
    },
    {
      "molecule_id": "BH2+_singlet_C2v",
      "basis": "sto-3g",
      "status": "complete",
      "n_alphas": 10,
      "n_ok": 10,
      "n_fci_converged": 10,
      "n_spin_mismatch": 0,
      "elapsed_s": 0,
      "error": null,
      "alphas": []
    },
    {
      "molecule_id": "BH2N_singlet_Coov",
      "basis": "sto-3g",
      "status": "complete",
      "n_alphas": 10,
      "n_ok": 10,
      "n_fci_converged": 9,
      "n_spin_mismatch": 0,
      "elapsed_s": 0,
      "error": null,
      "alphas": []
    },
    {
      "molecule_id": "BH3_singlet_C2v",
      "basis": "sto-3g",
      "status": "complete",
      "n_alphas": 10,
      "n_ok": 10,
      "n_fci_converged": 10,
      "n_spin_mismatch": 0,
      "elapsed_s": 0,
      "error": null,
      "alphas": []
    },
    {
      "molecule_id": "BH4-_singlet_D2d",
      "basis": "sto-3g",
      "status": "complete",
      "n_alphas": 10,
      "n_ok": 10,
      "n_fci_converged": 10,
      "n_spin_mismatch": 0,
      "elapsed_s": 0,
      "error": null,
      "alphas": []
    },
    {
      "molecule_id": "BHO_singlet_Coov",
      "basis": "sto-3g",
      "status": "complete",
      "n_alphas": 10,
      "n_ok": 10,
      "n_fci_converged": 10,
      "n_spin_mismatch": 0,
      "elapsed_s": 0,
      "error": null,
      "alphas": []
    },
    {
      "molecule_id": "BH_singlet_Coov",
      "basis": "3-21g",
      "status": "complete",
      "n_alphas": 10,
      "n_ok": 10,
      "n_fci_converged": 10,
      "n_spin_mismatch": 0,
      "elapsed_s": 0,
      "error": null,
      "alphas": []
    },
    {
      "molecule_id": "BH_singlet_Coov",
      "basis": "sto-3g",
      "status": "complete",
      "n_alphas": 10,
      "n_ok": 10,
      "n_fci_converged": 10,
      "n_spin_mismatch": 0,
      "elapsed_s": 0,
      "error": null,
      "alphas": []
    },
    {
      "molecule_id": "BO+_singlet_Coov",
      "basis": "sto-3g",
      "status": "complete",
      "n_alphas": 10,
      "n_ok": 10,
      "n_fci_converged": 10,
      "n_spin_mismatch": 0,
      "elapsed_s": 0,
      "error": null,
      "alphas": []
    },
    {
      "molecule_id": "BO-_singlet_Coov",
      "basis": "sto-3g",
      "status": "complete",
      "n_alphas": 10,
      "n_ok": 10,
      "n_fci_converged": 10,
      "n_spin_mismatch": 0,
      "elapsed_s": 0,
      "error": null,
      "alphas": []
    },
    {
      "molecule_id": "Be2_singlet_Dooh",
      "basis": "sto-3g",
      "status": "complete",
      "n_alphas": 10,
      "n_ok": 10,
      "n_fci_converged": 10,
      "n_spin_mismatch": 0,
      "elapsed_s": 0,
      "error": null,
      "alphas": []
    },
    {
      "molecule_id": "BeF+_singlet_Coov",
      "basis": "sto-3g",
      "status": "complete",
      "n_alphas": 10,
      "n_ok": 10,
      "n_fci_converged": 10,
      "n_spin_mismatch": 0,
      "elapsed_s": 0,
      "error": null,
      "alphas": []
    },
    {
      "molecule_id": "BeF-_singlet_Coov",
      "basis": "sto-3g",
      "status": "complete",
      "n_alphas": 10,
      "n_ok": 10,
      "n_fci_converged": 10,
      "n_spin_mismatch": 0,
      "elapsed_s": 0,
      "error": null,
      "alphas": []
    },
    {
      "molecule_id": "BeH+_singlet_Coov",
      "basis": "3-21g",
      "status": "complete",
      "n_alphas": 10,
      "n_ok": 10,
      "n_fci_converged": 10,
      "n_spin_mismatch": 0,
      "elapsed_s": 0,
      "error": null,
      "alphas": []
    },
    {
      "molecule_id": "BeH+_singlet_Coov",
      "basis": "sto-3g",
      "status": "complete",
      "n_alphas": 10,
      "n_ok": 10,
      "n_fci_converged": 10,
      "n_spin_mismatch": 0,
      "elapsed_s": 0,
      "error": null,
      "alphas": []
    },
    {
      "molecule_id": "BeH-_singlet_Coov",
      "basis": "3-21g",
      "status": "complete",
      "n_alphas": 10,
      "n_ok": 10,
      "n_fci_converged": 10,
      "n_spin_mismatch": 0,
      "elapsed_s": 0,
      "error": null,
      "alphas": []
    },
    {
      "molecule_id": "BeH-_singlet_Coov",
      "basis": "sto-3g",
      "status": "complete",
      "n_alphas": 10,
      "n_ok": 10,
      "n_fci_converged": 10,
      "n_spin_mismatch": 0,
      "elapsed_s": 0,
      "error": null,
      "alphas": []
    },
    {
      "molecule_id": "BeH2_singlet_Dooh",
      "basis": "sto-3g",
      "status": "complete",
      "n_alphas": 10,
      "n_ok": 10,
      "n_fci_converged": 10,
      "n_spin_mismatch": 0,
      "elapsed_s": 0,
      "error": null,
      "alphas": []
    },
    {
      "molecule_id": "BeN-_singlet_Coov",
      "basis": "sto-3g",
      "status": "complete",
      "n_alphas": 10,
      "n_ok": 10,
      "n_fci_converged": 10,
      "n_spin_mismatch": 0,
      "elapsed_s": 0,
      "error": null,
      "alphas": []
    },
    {
      "molecule_id": "BeO_singlet_Coov",
      "basis": "sto-3g",
      "status": "complete",
      "n_alphas": 10,
      "n_ok": 10,
      "n_fci_converged": 10,
      "n_spin_mismatch": 0,
      "elapsed_s": 0,
      "error": null,
      "alphas": []
    },
    {
      "molecule_id": "Be_singlet_Kh",
      "basis": "3-21g",
      "status": "complete",
      "n_alphas": 1,
      "n_ok": 1,
      "n_fci_converged": 1,
      "n_spin_mismatch": 0,
      "elapsed_s": 0,
      "error": null,
      "alphas": []
    },
    {
      "molecule_id": "Be_singlet_Kh",
      "basis": "sto-3g",
      "status": "complete",
      "n_alphas": 1,
      "n_ok": 1,
      "n_fci_converged": 1,
      "n_spin_mismatch": 0,
      "elapsed_s": 0,
      "error": null,
      "alphas": []
    },
    {
      "molecule_id": "C2H-_singlet_Cs",
      "basis": "sto-3g",
      "status": "complete",
      "n_alphas": 10,
      "n_ok": 10,
      "n_fci_converged": 10,
      "n_spin_mismatch": 0,
      "elapsed_s": 0,
      "error": null,
      "alphas": []
    },
    {
      "molecule_id": "C2H2_singlet_C2v",
      "basis": "sto-3g",
      "status": "complete",
      "n_alphas": 10,
      "n_ok": 10,
      "n_fci_converged": 9,
      "n_spin_mismatch": 0,
      "elapsed_s": 0,
      "error": null,
      "alphas": []
    },
    {
      "molecule_id": "C2H2_singlet_Dooh",
      "basis": "sto-3g",
      "status": "complete",
      "n_alphas": 10,
      "n_ok": 10,
      "n_fci_converged": 9,
      "n_spin_mismatch": 0,
      "elapsed_s": 0,
      "error": null,
      "alphas": []
    },
    {
      "molecule_id": "C2_singlet_Dooh",
      "basis": "sto-3g",
      "status": "complete",
      "n_alphas": 10,
      "n_ok": 10,
      "n_fci_converged": 9,
      "n_spin_mismatch": 0,
      "elapsed_s": 0,
      "error": null,
      "alphas": []
    },
    {
      "molecule_id": "CD4_singlet_Td",
      "basis": "sto-3g",
      "status": "complete",
      "n_alphas": 10,
      "n_ok": 10,
      "n_fci_converged": 10,
      "n_spin_mismatch": 0,
      "elapsed_s": 0,
      "error": null,
      "alphas": []
    },
    {
      "molecule_id": "CF+_singlet_Coov",
      "basis": "sto-3g",
      "status": "complete",
      "n_alphas": 10,
      "n_ok": 10,
      "n_fci_converged": 10,
      "n_spin_mismatch": 0,
      "elapsed_s": 0,
      "error": null,
      "alphas": []
    },
    {
      "molecule_id": "CH+_singlet_Coov",
      "basis": "3-21g",
      "status": "complete",
      "n_alphas": 10,
      "n_ok": 10,
      "n_fci_converged": 10,
      "n_spin_mismatch": 0,
      "elapsed_s": 0,
      "error": null,
      "alphas": []
    },
    {
      "molecule_id": "CH+_singlet_Coov",
      "basis": "sto-3g",
      "status": "complete",
      "n_alphas": 10,
      "n_ok": 10,
      "n_fci_converged": 10,
      "n_spin_mismatch": 0,
      "elapsed_s": 0,
      "error": null,
      "alphas": []
    },
    {
      "molecule_id": "CH-_singlet_Coov",
      "basis": "3-21g",
      "status": "complete",
      "n_alphas": 10,
      "n_ok": 10,
      "n_fci_converged": 10,
      "n_spin_mismatch": 0,
      "elapsed_s": 0,
      "error": null,
      "alphas": []
    },
    {
      "molecule_id": "CH-_singlet_Coov",
      "basis": "sto-3g",
      "status": "complete",
      "n_alphas": 10,
      "n_ok": 10,
      "n_fci_converged": 10,
      "n_spin_mismatch": 0,
      "elapsed_s": 0,
      "error": null,
      "alphas": []
    },
    {
      "molecule_id": "CH2D2_singlet_C2v",
      "basis": "sto-3g",
      "status": "complete",
      "n_alphas": 10,
      "n_ok": 10,
      "n_fci_converged": 10,
      "n_spin_mismatch": 0,
      "elapsed_s": 0,
      "error": null,
      "alphas": []
    },
    {
      "molecule_id": "CH2N+_singlet_C2v",
      "basis": "sto-3g",
      "status": "complete",
      "n_alphas": 10,
      "n_ok": 10,
      "n_fci_converged": 10,
      "n_spin_mismatch": 0,
      "elapsed_s": 0,
      "error": null,
      "alphas": []
    },
    {
      "molecule_id": "CH2N+_singlet_C2v_2",
      "basis": "sto-3g",
      "status": "complete",
      "n_alphas": 10,
      "n_ok": 10,
      "n_fci_converged": 10,
      "n_spin_mismatch": 0,
      "elapsed_s": 0,
      "error": null,
      "alphas": []
    },
    {
      "molecule_id": "CH2O_singlet_C2v",
      "basis": "sto-3g",
      "status": "complete",
      "n_alphas": 10,
      "n_ok": 10,
      "n_fci_converged": 9,
      "n_spin_mismatch": 0,
      "elapsed_s": 0,
      "error": null,
      "alphas": []
    },
    {
      "molecule_id": "CH3+_singlet_D3h",
      "basis": "sto-3g",
      "status": "complete",
      "n_alphas": 10,
      "n_ok": 10,
      "n_fci_converged": 10,
      "n_spin_mismatch": 0,
      "elapsed_s": 0,
      "error": null,
      "alphas": []
    },
    {
      "molecule_id": "CH3-_singlet_D3h",
      "basis": "sto-3g",
      "status": "complete",
      "n_alphas": 10,
      "n_ok": 10,
      "n_fci_converged": 10,
      "n_spin_mismatch": 0,
      "elapsed_s": 0,
      "error": null,
      "alphas": []
    },
    {
      "molecule_id": "CH3D_singlet_C3v",
      "basis": "sto-3g",
      "status": "complete",
      "n_alphas": 10,
      "n_ok": 10,
      "n_fci_converged": 9,
      "n_spin_mismatch": 0,
      "elapsed_s": 0,
      "error": null,
      "alphas": []
    },
    {
      "molecule_id": "CH4_singlet_Td",
      "basis": "sto-3g",
      "status": "complete",
      "n_alphas": 10,
      "n_ok": 10,
      "n_fci_converged": 9,
      "n_spin_mismatch": 0,
      "elapsed_s": 0,
      "error": null,
      "alphas": []
    },
    {
      "molecule_id": "CHD3_singlet_C3v",
      "basis": "sto-3g",
      "status": "complete",
      "n_alphas": 10,
      "n_ok": 10,
      "n_fci_converged": 9,
      "n_spin_mismatch": 0,
      "elapsed_s": 0,
      "error": null,
      "alphas": []
    },
    {
      "molecule_id": "CHF_singlet_Cs",
      "basis": "sto-3g",
      "status": "complete",
      "n_alphas": 10,
      "n_ok": 10,
      "n_fci_converged": 9,
      "n_spin_mismatch": 0,
      "elapsed_s": 0,
      "error": null,
      "alphas": []
    },
    {
      "molecule_id": "CHN_singlet_Coov",
      "basis": "sto-3g",
      "status": "complete",
      "n_alphas": 10,
      "n_ok": 10,
      "n_fci_converged": 10,
      "n_spin_mismatch": 0,
      "elapsed_s": 0,
      "error": null,
      "alphas": []
    },
    {
      "molecule_id": "CHN_singlet_Coov_2",
      "basis": "sto-3g",
      "status": "complete",
      "n_alphas": 10,
      "n_ok": 10,
      "n_fci_converged": 10,
      "n_spin_mismatch": 0,
      "elapsed_s": 0,
      "error": null,
      "alphas": []
    },
    {
      "molecule_id": "CHO+_singlet_Cs",
      "basis": "sto-3g",
      "status": "complete",
      "n_alphas": 10,
      "n_ok": 10,
      "n_fci_converged": 10,
      "n_spin_mismatch": 0,
      "elapsed_s": 0,
      "error": null,
      "alphas": []
    },
    {
      "molecule_id": "CHO+_singlet_Cs_2",
      "basis": "sto-3g",
      "status": "complete",
      "n_alphas": 10,
      "n_ok": 10,
      "n_fci_converged": 10,
      "n_spin_mismatch": 0,
      "elapsed_s": 0,
      "error": null,
      "alphas": []
    },
    {
      "molecule_id": "CHO-_singlet_Cs",
      "basis": "sto-3g",
      "status": "complete",
      "n_alphas": 10,
      "n_ok": 10,
      "n_fci_converged": 8,
      "n_spin_mismatch": 0,
      "elapsed_s": 0,
      "error": null,
      "alphas": []
    },
    {
      "molecule_id": "CN+_singlet_Coov",
      "basis": "sto-3g",
      "status": "complete",
      "n_alphas": 10,
      "n_ok": 10,
      "n_fci_converged": 10,
      "n_spin_mismatch": 0,
      "elapsed_s": 0,
      "error": null,
      "alphas": []
    },
    {
      "molecule_id": "CN-_singlet_Coov",
      "basis": "sto-3g",
      "status": "complete",
      "n_alphas": 10,
      "n_ok": 10,
      "n_fci_converged": 10,
      "n_spin_mismatch": 0,
      "elapsed_s": 0,
      "error": null,
      "alphas": []
    },
    {
      "molecule_id": "CO_singlet_Coov",
      "basis": "sto-3g",
      "status": "complete",
      "n_alphas": 10,
      "n_ok": 10,
      "n_fci_converged": 10,
      "n_spin_mismatch": 0,
      "elapsed_s": 0,
      "error": null,
      "alphas": []
    },
    {
      "molecule_id": "Cl-_singlet_Kh",
      "basis": "sto-3g",
      "status": "complete",
      "n_alphas": 1,
      "n_ok": 1,
      "n_fci_converged": 1,
      "n_spin_mismatch": 0,
      "elapsed_s": 0,
      "error": null,
      "alphas": []
    },
    {
      "molecule_id": "ClD_singlet_Coov",
      "basis": "sto-3g",
      "status": "complete",
      "n_alphas": 10,
      "n_ok": 10,
      "n_fci_converged": 10,
      "n_spin_mismatch": 0,
      "elapsed_s": 0,
      "error": null,
      "alphas": []
    },
    {
      "molecule_id": "ClH2+_singlet_C1",
      "basis": "sto-3g",
      "status": "complete",
      "n_alphas": 10,
      "n_ok": 10,
      "n_fci_converged": 10,
      "n_spin_mismatch": 0,
      "elapsed_s": 0,
      "error": null,
      "alphas": []
    },
    {
      "molecule_id": "ClH_singlet_Coov",
      "basis": "sto-3g",
      "status": "complete",
      "n_alphas": 10,
      "n_ok": 10,
      "n_fci_converged": 10,
      "n_spin_mismatch": 0,
      "elapsed_s": 0,
      "error": null,
      "alphas": []
    },
    {
      "molecule_id": "D2O_singlet_C2v",
      "basis": "sto-3g",
      "status": "complete",
      "n_alphas": 10,
      "n_ok": 10,
      "n_fci_converged": 10,
      "n_spin_mismatch": 0,
      "elapsed_s": 0,
      "error": null,
      "alphas": []
    },
    {
      "molecule_id": "D2S_singlet_C2v",
      "basis": "sto-3g",
      "status": "complete",
      "n_alphas": 10,
      "n_ok": 10,
      "n_fci_converged": 10,
      "n_spin_mismatch": 0,
      "elapsed_s": 0,
      "error": null,
      "alphas": []
    },
    {
      "molecule_id": "D2_singlet_Dooh",
      "basis": "3-21g",
      "status": "complete",
      "n_alphas": 10,
      "n_ok": 10,
      "n_fci_converged": 10,
      "n_spin_mismatch": 0,
      "elapsed_s": 0,
      "error": null,
      "alphas": []
    },
    {
      "molecule_id": "D2_singlet_Dooh",
      "basis": "6-311g**",
      "status": "complete",
      "n_alphas": 10,
      "n_ok": 10,
      "n_fci_converged": 10,
      "n_spin_mismatch": 0,
      "elapsed_s": 0,
      "error": null,
      "alphas": []
    },
    {
      "molecule_id": "D2_singlet_Dooh",
      "basis": "6-31g**",
      "status": "complete",
      "n_alphas": 10,
      "n_ok": 10,
      "n_fci_converged": 10,
      "n_spin_mismatch": 0,
      "elapsed_s": 0,
      "error": null,
      "alphas": []
    },
    {
      "molecule_id": "D2_singlet_Dooh",
      "basis": "cc-pvdz",
      "status": "complete",
      "n_alphas": 10,
      "n_ok": 10,
      "n_fci_converged": 10,
      "n_spin_mismatch": 0,
      "elapsed_s": 0,
      "error": null,
      "alphas": []
    },
    {
      "molecule_id": "D2_singlet_Dooh",
      "basis": "sto-3g",
      "status": "complete",
      "n_alphas": 10,
      "n_ok": 10,
      "n_fci_converged": 10,
      "n_spin_mismatch": 0,
      "elapsed_s": 0,
      "error": null,
      "alphas": []
    },
    {
      "molecule_id": "D3N_singlet_C3v",
      "basis": "sto-3g",
      "status": "complete",
      "n_alphas": 10,
      "n_ok": 10,
      "n_fci_converged": 10,
      "n_spin_mismatch": 0,
      "elapsed_s": 0,
      "error": null,
      "alphas": []
    },
    {
      "molecule_id": "DF_singlet_Coov",
      "basis": "3-21g",
      "status": "complete",
      "n_alphas": 10,
      "n_ok": 10,
      "n_fci_converged": 10,
      "n_spin_mismatch": 0,
      "elapsed_s": 0,
      "error": null,
      "alphas": []
    },
    {
      "molecule_id": "DF_singlet_Coov",
      "basis": "sto-3g",
      "status": "complete",
      "n_alphas": 10,
      "n_ok": 10,
      "n_fci_converged": 10,
      "n_spin_mismatch": 0,
      "elapsed_s": 0,
      "error": null,
      "alphas": []
    },
    {
      "molecule_id": "DHO_singlet_Cs",
      "basis": "sto-3g",
      "status": "complete",
      "n_alphas": 10,
      "n_ok": 10,
      "n_fci_converged": 10,
      "n_spin_mismatch": 0,
      "elapsed_s": 0,
      "error": null,
      "alphas": []
    },
    {
      "molecule_id": "DH_singlet_Coov",
      "basis": "3-21g",
      "status": "complete",
      "n_alphas": 10,
      "n_ok": 10,
      "n_fci_converged": 10,
      "n_spin_mismatch": 0,
      "elapsed_s": 0,
      "error": null,
      "alphas": []
    },
    {
      "molecule_id": "DH_singlet_Coov",
      "basis": "6-311g**",
      "status": "complete",
      "n_alphas": 10,
      "n_ok": 10,
      "n_fci_converged": 10,
      "n_spin_mismatch": 0,
      "elapsed_s": 0,
      "error": null,
      "alphas": []
    },
    {
      "molecule_id": "DH_singlet_Coov",
      "basis": "6-31g**",
      "status": "complete",
      "n_alphas": 10,
      "n_ok": 10,
      "n_fci_converged": 10,
      "n_spin_mismatch": 0,
      "elapsed_s": 0,
      "error": null,
      "alphas": []
    },
    {
      "molecule_id": "DH_singlet_Coov",
      "basis": "cc-pvdz",
      "status": "complete",
      "n_alphas": 10,
      "n_ok": 10,
      "n_fci_converged": 10,
      "n_spin_mismatch": 0,
      "elapsed_s": 0,
      "error": null,
      "alphas": []
    },
    {
      "molecule_id": "DH_singlet_Coov",
      "basis": "sto-3g",
      "status": "complete",
      "n_alphas": 10,
      "n_ok": 10,
      "n_fci_converged": 10,
      "n_spin_mismatch": 0,
      "elapsed_s": 0,
      "error": null,
      "alphas": []
    },
    {
      "molecule_id": "F-_singlet_Kh",
      "basis": "3-21g",
      "status": "complete",
      "n_alphas": 1,
      "n_ok": 1,
      "n_fci_converged": 1,
      "n_spin_mismatch": 0,
      "elapsed_s": 0,
      "error": null,
      "alphas": []
    },
    {
      "molecule_id": "F-_singlet_Kh",
      "basis": "sto-3g",
      "status": "complete",
      "n_alphas": 1,
      "n_ok": 1,
      "n_fci_converged": 1,
      "n_spin_mismatch": 0,
      "elapsed_s": 0,
      "error": null,
      "alphas": []
    },
    {
      "molecule_id": "F2H+_singlet_C1",
      "basis": "sto-3g",
      "status": "complete",
      "n_alphas": 10,
      "n_ok": 10,
      "n_fci_converged": 10,
      "n_spin_mismatch": 0,
      "elapsed_s": 0,
      "error": null,
      "alphas": []
    },
    {
      "molecule_id": "F2H-_singlet_Dooh",
      "basis": "sto-3g",
      "status": "complete",
      "n_alphas": 10,
      "n_ok": 10,
      "n_fci_converged": 10,
      "n_spin_mismatch": 0,
      "elapsed_s": 0,
      "error": null,
      "alphas": []
    },
    {
      "molecule_id": "F2_singlet_Dooh",
      "basis": "sto-3g",
      "status": "complete",
      "n_alphas": 10,
      "n_ok": 10,
      "n_fci_converged": 10,
      "n_spin_mismatch": 0,
      "elapsed_s": 0,
      "error": null,
      "alphas": []
    },
    {
      "molecule_id": "FH2+_singlet_C1",
      "basis": "sto-3g",
      "status": "complete",
      "n_alphas": 10,
      "n_ok": 10,
      "n_fci_converged": 10,
      "n_spin_mismatch": 0,
      "elapsed_s": 0,
      "error": null,
      "alphas": []
    },
    {
      "molecule_id": "FHO_singlet_Cs",
      "basis": "sto-3g",
      "status": "complete",
      "n_alphas": 10,
      "n_ok": 10,
      "n_fci_converged": 9,
      "n_spin_mismatch": 0,
      "elapsed_s": 0,
      "error": null,
      "alphas": []
    },
    {
      "molecule_id": "FH_singlet_Coov",
      "basis": "3-21g",
      "status": "complete",
      "n_alphas": 10,
      "n_ok": 10,
      "n_fci_converged": 10,
      "n_spin_mismatch": 0,
      "elapsed_s": 0,
      "error": null,
      "alphas": []
    },
    {
      "molecule_id": "FH_singlet_Coov",
      "basis": "sto-3g",
      "status": "complete",
      "n_alphas": 10,
      "n_ok": 10,
      "n_fci_converged": 10,
      "n_spin_mismatch": 0,
      "elapsed_s": 0,
      "error": null,
      "alphas": []
    },
    {
      "molecule_id": "FLi_singlet_Coov",
      "basis": "sto-3g",
      "status": "complete",
      "n_alphas": 10,
      "n_ok": 10,
      "n_fci_converged": 10,
      "n_spin_mismatch": 0,
      "elapsed_s": 0,
      "error": null,
      "alphas": []
    },
    {
      "molecule_id": "FO+_singlet_Coov",
      "basis": "sto-3g",
      "status": "complete",
      "n_alphas": 10,
      "n_ok": 10,
      "n_fci_converged": 10,
      "n_spin_mismatch": 0,
      "elapsed_s": 0,
      "error": null,
      "alphas": []
    },
    {
      "molecule_id": "FO-_singlet_Coov",
      "basis": "sto-3g",
      "status": "complete",
      "n_alphas": 10,
      "n_ok": 10,
      "n_fci_converged": 10,
      "n_spin_mismatch": 0,
      "elapsed_s": 0,
      "error": null,
      "alphas": []
    },
    {
      "molecule_id": "H+_singlet_Kh",
      "basis": "3-21g",
      "status": "complete",
      "n_alphas": 1,
      "n_ok": 1,
      "n_fci_converged": 1,
      "n_spin_mismatch": 0,
      "elapsed_s": 0,
      "error": null,
      "alphas": []
    },
    {
      "molecule_id": "H+_singlet_Kh",
      "basis": "6-311g**",
      "status": "complete",
      "n_alphas": 1,
      "n_ok": 1,
      "n_fci_converged": 1,
      "n_spin_mismatch": 0,
      "elapsed_s": 0,
      "error": null,
      "alphas": []
    },
    {
      "molecule_id": "H+_singlet_Kh",
      "basis": "6-31g**",
      "status": "complete",
      "n_alphas": 1,
      "n_ok": 1,
      "n_fci_converged": 1,
      "n_spin_mismatch": 0,
      "elapsed_s": 0,
      "error": null,
      "alphas": []
    },
    {
      "molecule_id": "H+_singlet_Kh",
      "basis": "cc-pvdz",
      "status": "complete",
      "n_alphas": 1,
      "n_ok": 1,
      "n_fci_converged": 1,
      "n_spin_mismatch": 0,
      "elapsed_s": 0,
      "error": null,
      "alphas": []
    },
    {
      "molecule_id": "H+_singlet_Kh",
      "basis": "sto-3g",
      "status": "complete",
      "n_alphas": 1,
      "n_ok": 1,
      "n_fci_converged": 1,
      "n_spin_mismatch": 0,
      "elapsed_s": 0,
      "error": null,
      "alphas": []
    },
    {
      "molecule_id": "H-_singlet_Kh",
      "basis": "3-21g",
      "status": "complete",
      "n_alphas": 1,
      "n_ok": 1,
      "n_fci_converged": 1,
      "n_spin_mismatch": 0,
      "elapsed_s": 0,
      "error": null,
      "alphas": []
    },
    {
      "molecule_id": "H-_singlet_Kh",
      "basis": "6-311g**",
      "status": "complete",
      "n_alphas": 1,
      "n_ok": 1,
      "n_fci_converged": 1,
      "n_spin_mismatch": 0,
      "elapsed_s": 0,
      "error": null,
      "alphas": []
    },
    {
      "molecule_id": "H-_singlet_Kh",
      "basis": "6-31g**",
      "status": "complete",
      "n_alphas": 1,
      "n_ok": 1,
      "n_fci_converged": 1,
      "n_spin_mismatch": 0,
      "elapsed_s": 0,
      "error": null,
      "alphas": []
    },
    {
      "molecule_id": "H-_singlet_Kh",
      "basis": "cc-pvdz",
      "status": "complete",
      "n_alphas": 1,
      "n_ok": 1,
      "n_fci_converged": 1,
      "n_spin_mismatch": 0,
      "elapsed_s": 0,
      "error": null,
      "alphas": []
    },
    {
      "molecule_id": "H-_singlet_Kh",
      "basis": "sto-3g",
      "status": "complete",
      "n_alphas": 1,
      "n_ok": 1,
      "n_fci_converged": 1,
      "n_spin_mismatch": 0,
      "elapsed_s": 0,
      "error": null,
      "alphas": []
    },
    {
      "molecule_id": "H2LiN_singlet_C2v",
      "basis": "sto-3g",
      "status": "complete",
      "n_alphas": 10,
      "n_ok": 10,
      "n_fci_converged": 10,
      "n_spin_mismatch": 0,
      "elapsed_s": 0,
      "error": null,
      "alphas": []
    },
    {
      "molecule_id": "H2Mg_singlet_Dooh",
      "basis": "sto-3g",
      "status": "complete",
      "n_alphas": 10,
      "n_ok": 10,
      "n_fci_converged": 10,
      "n_spin_mismatch": 0,
      "elapsed_s": 0,
      "error": null,
      "alphas": []
    },
    {
      "molecule_id": "H2N-_singlet_C2v",
      "basis": "sto-3g",
      "status": "complete",
      "n_alphas": 10,
      "n_ok": 10,
      "n_fci_converged": 10,
      "n_spin_mismatch": 0,
      "elapsed_s": 0,
      "error": null,
      "alphas": []
    },
    {
      "molecule_id": "H2N2_singlet_C2v",
      "basis": "sto-3g",
      "status": "complete",
      "n_alphas": 10,
      "n_ok": 10,
      "n_fci_converged": 9,
      "n_spin_mismatch": 0,
      "elapsed_s": 0,
      "error": null,
      "alphas": []
    },
    {
      "molecule_id": "H2N2_singlet_C2h",
      "basis": "sto-3g",
      "status": "complete",
      "n_alphas": 10,
      "n_ok": 10,
      "n_fci_converged": 9,
      "n_spin_mismatch": 0,
      "elapsed_s": 0,
      "error": null,
      "alphas": []
    },
    {
      "molecule_id": "H2N2_singlet_C2v_2",
      "basis": "sto-3g",
      "status": "complete",
      "n_alphas": 10,
      "n_ok": 10,
      "n_fci_converged": 10,
      "n_spin_mismatch": 0,
      "elapsed_s": 0,
      "error": null,
      "alphas": []
    },
    {
      "molecule_id": "H2O2_singlet_C2h",
      "basis": "sto-3g",
      "status": "complete",
      "n_alphas": 10,
      "n_ok": 10,
      "n_fci_converged": 8,
      "n_spin_mismatch": 0,
      "elapsed_s": 0,
      "error": null,
      "alphas": []
    },
    {
      "molecule_id": "H2O_singlet_C2v",
      "basis": "sto-3g",
      "status": "complete",
      "n_alphas": 10,
      "n_ok": 10,
      "n_fci_converged": 10,
      "n_spin_mismatch": 0,
      "elapsed_s": 0,
      "error": null,
      "alphas": []
    },
    {
      "molecule_id": "H2P+_singlet_C2v",
      "basis": "sto-3g",
      "status": "complete",
      "n_alphas": 10,
      "n_ok": 10,
      "n_fci_converged": 10,
      "n_spin_mismatch": 0,
      "elapsed_s": 0,
      "error": null,
      "alphas": []
    },
    {
      "molecule_id": "H2P-_singlet_C2v",
      "basis": "sto-3g",
      "status": "complete",
      "n_alphas": 10,
      "n_ok": 10,
      "n_fci_converged": 10,
      "n_spin_mismatch": 0,
      "elapsed_s": 0,
      "error": null,
      "alphas": []
    },
    {
      "molecule_id": "H2S_singlet_C2v",
      "basis": "sto-3g",
      "status": "complete",
      "n_alphas": 10,
      "n_ok": 10,
      "n_fci_converged": 10,
      "n_spin_mismatch": 0,
      "elapsed_s": 0,
      "error": null,
      "alphas": []
    },
    {
      "molecule_id": "H2Si_singlet_C2v",
      "basis": "sto-3g",
      "status": "complete",
      "n_alphas": 10,
      "n_ok": 10,
      "n_fci_converged": 10,
      "n_spin_mismatch": 0,
      "elapsed_s": 0,
      "error": null,
      "alphas": []
    },
    {
      "molecule_id": "H2_singlet_Dooh",
      "basis": "3-21g",
      "status": "complete",
      "n_alphas": 10,
      "n_ok": 10,
      "n_fci_converged": 10,
      "n_spin_mismatch": 0,
      "elapsed_s": 0,
      "error": null,
      "alphas": []
    },
    {
      "molecule_id": "H2_singlet_Dooh",
      "basis": "6-311g**",
      "status": "complete",
      "n_alphas": 10,
      "n_ok": 10,
      "n_fci_converged": 10,
      "n_spin_mismatch": 0,
      "elapsed_s": 0,
      "error": null,
      "alphas": []
    },
    {
      "molecule_id": "H2_singlet_Dooh",
      "basis": "6-31g**",
      "status": "complete",
      "n_alphas": 10,
      "n_ok": 10,
      "n_fci_converged": 10,
      "n_spin_mismatch": 0,
      "elapsed_s": 0,
      "error": null,
      "alphas": []
    },
    {
      "molecule_id": "H2_singlet_Dooh",
      "basis": "cc-pvdz",
      "status": "complete",
      "n_alphas": 10,
      "n_ok": 10,
      "n_fci_converged": 10,
      "n_spin_mismatch": 0,
      "elapsed_s": 0,
      "error": null,
      "alphas": []
    },
    {
      "molecule_id": "H2_singlet_Dooh",
      "basis": "sto-3g",
      "status": "complete",
      "n_alphas": 10,
      "n_ok": 10,
      "n_fci_converged": 10,
      "n_spin_mismatch": 0,
      "elapsed_s": 0,
      "error": null,
      "alphas": []
    },
    {
      "molecule_id": "H3+_singlet_C1",
      "basis": "3-21g",
      "status": "complete",
      "n_alphas": 10,
      "n_ok": 10,
      "n_fci_converged": 10,
      "n_spin_mismatch": 0,
      "elapsed_s": 0,
      "error": null,
      "alphas": []
    },
    {
      "molecule_id": "H3+_singlet_C1",
      "basis": "sto-3g",
      "status": "complete",
      "n_alphas": 10,
      "n_ok": 10,
      "n_fci_converged": 10,
      "n_spin_mismatch": 0,
      "elapsed_s": 0,
      "error": null,
      "alphas": []
    },
    {
      "molecule_id": "H3N_singlet_C3v",
      "basis": "sto-3g",
      "status": "complete",
      "n_alphas": 10,
      "n_ok": 10,
      "n_fci_converged": 10,
      "n_spin_mismatch": 0,
      "elapsed_s": 0,
      "error": null,
      "alphas": []
    },
    {
      "molecule_id": "H3O+_singlet_C1",
      "basis": "sto-3g",
      "status": "complete",
      "n_alphas": 10,
      "n_ok": 10,
      "n_fci_converged": 10,
      "n_spin_mismatch": 0,
      "elapsed_s": 0,
      "error": null,
      "alphas": []
    },
    {
      "molecule_id": "H4N+_singlet_Td",
      "basis": "sto-3g",
      "status": "complete",
      "n_alphas": 10,
      "n_ok": 10,
      "n_fci_converged": 10,
      "n_spin_mismatch": 0,
      "elapsed_s": 0,
      "error": null,
      "alphas": []
    },
    {
      "molecule_id": "HHe+_singlet_Coov",
      "basis": "3-21g",
      "status": "complete",
      "n_alphas": 10,
      "n_ok": 10,
      "n_fci_converged": 10,
      "n_spin_mismatch": 0,
      "elapsed_s": 0,
      "error": null,
      "alphas": []
    },
    {
      "molecule_id": "HHe+_singlet_Coov",
      "basis": "6-311g**",
      "status": "complete",
      "n_alphas": 10,
      "n_ok": 10,
      "n_fci_converged": 10,
      "n_spin_mismatch": 0,
      "elapsed_s": 0,
      "error": null,
      "alphas": []
    },
    {
      "molecule_id": "HHe+_singlet_Coov",
      "basis": "6-31g**",
      "status": "complete",
      "n_alphas": 10,
      "n_ok": 10,
      "n_fci_converged": 10,
      "n_spin_mismatch": 0,
      "elapsed_s": 0,
      "error": null,
      "alphas": []
    },
    {
      "molecule_id": "HHe+_singlet_Coov",
      "basis": "cc-pvdz",
      "status": "complete",
      "n_alphas": 10,
      "n_ok": 10,
      "n_fci_converged": 10,
      "n_spin_mismatch": 0,
      "elapsed_s": 0,
      "error": null,
      "alphas": []
    },
    {
      "molecule_id": "HHe+_singlet_Coov",
      "basis": "sto-3g",
      "status": "complete",
      "n_alphas": 10,
      "n_ok": 10,
      "n_fci_converged": 10,
      "n_spin_mismatch": 0,
      "elapsed_s": 0,
      "error": null,
      "alphas": []
    },
    {
      "molecule_id": "HLiO_singlet_Coov",
      "basis": "sto-3g",
      "status": "complete",
      "n_alphas": 10,
      "n_ok": 10,
      "n_fci_converged": 10,
      "n_spin_mismatch": 0,
      "elapsed_s": 0,
      "error": null,
      "alphas": []
    },
    {
      "molecule_id": "HLi_singlet_Coov",
      "basis": "3-21g",
      "status": "complete",
      "n_alphas": 10,
      "n_ok": 10,
      "n_fci_converged": 10,
      "n_spin_mismatch": 0,
      "elapsed_s": 0,
      "error": null,
      "alphas": []
    },
    {
      "molecule_id": "HLi_singlet_Coov",
      "basis": "sto-3g",
      "status": "complete",
      "n_alphas": 10,
      "n_ok": 10,
      "n_fci_converged": 10,
      "n_spin_mismatch": 0,
      "elapsed_s": 0,
      "error": null,
      "alphas": []
    },
    {
      "molecule_id": "HMg+_singlet_Coov",
      "basis": "sto-3g",
      "status": "complete",
      "n_alphas": 10,
      "n_ok": 10,
      "n_fci_converged": 10,
      "n_spin_mismatch": 0,
      "elapsed_s": 0,
      "error": null,
      "alphas": []
    },
    {
      "molecule_id": "HMg-_singlet_Coov",
      "basis": "sto-3g",
      "status": "complete",
      "n_alphas": 10,
      "n_ok": 10,
      "n_fci_converged": 10,
      "n_spin_mismatch": 0,
      "elapsed_s": 0,
      "error": null,
      "alphas": []
    },
    {
      "molecule_id": "HN2+_singlet_Cs",
      "basis": "sto-3g",
      "status": "complete",
      "n_alphas": 10,
      "n_ok": 10,
      "n_fci_converged": 10,
      "n_spin_mismatch": 0,
      "elapsed_s": 0,
      "error": null,
      "alphas": []
    },
    {
      "molecule_id": "HNO_singlet_Cs",
      "basis": "sto-3g",
      "status": "complete",
      "n_alphas": 10,
      "n_ok": 10,
      "n_fci_converged": 10,
      "n_spin_mismatch": 0,
      "elapsed_s": 0,
      "error": null,
      "alphas": []
    },
    {
      "molecule_id": "HNO_singlet_Cs_2",
      "basis": "sto-3g",
      "status": "complete",
      "n_alphas": 10,
      "n_ok": 10,
      "n_fci_converged": 10,
      "n_spin_mismatch": 0,
      "elapsed_s": 0,
      "error": null,
      "alphas": []
    },
    {
      "molecule_id": "HNa_singlet_Coov",
      "basis": "sto-3g",
      "status": "complete",
      "n_alphas": 10,
      "n_ok": 10,
      "n_fci_converged": 10,
      "n_spin_mismatch": 0,
      "elapsed_s": 0,
      "error": null,
      "alphas": []
    },
    {
      "molecule_id": "HNe+_singlet_Coov",
      "basis": "3-21g",
      "status": "complete",
      "n_alphas": 10,
      "n_ok": 10,
      "n_fci_converged": 10,
      "n_spin_mismatch": 0,
      "elapsed_s": 0,
      "error": null,
      "alphas": []
    },
    {
      "molecule_id": "HNe+_singlet_Coov",
      "basis": "sto-3g",
      "status": "complete",
      "n_alphas": 10,
      "n_ok": 10,
      "n_fci_converged": 10,
      "n_spin_mismatch": 0,
      "elapsed_s": 0,
      "error": null,
      "alphas": []
    },
    {
      "molecule_id": "HO-_singlet_Coov",
      "basis": "3-21g",
      "status": "complete",
      "n_alphas": 10,
      "n_ok": 10,
      "n_fci_converged": 10,
      "n_spin_mismatch": 0,
      "elapsed_s": 0,
      "error": null,
      "alphas": []
    },
    {
      "molecule_id": "HO-_singlet_Coov",
      "basis": "sto-3g",
      "status": "complete",
      "n_alphas": 10,
      "n_ok": 10,
      "n_fci_converged": 10,
      "n_spin_mismatch": 0,
      "elapsed_s": 0,
      "error": null,
      "alphas": []
    },
    {
      "molecule_id": "HO2-_singlet_Coov",
      "basis": "sto-3g",
      "status": "complete",
      "n_alphas": 10,
      "n_ok": 10,
      "n_fci_converged": 9,
      "n_spin_mismatch": 0,
      "elapsed_s": 0,
      "error": null,
      "alphas": []
    },
    {
      "molecule_id": "HS-_singlet_Coov",
      "basis": "sto-3g",
      "status": "complete",
      "n_alphas": 10,
      "n_ok": 10,
      "n_fci_converged": 10,
      "n_spin_mismatch": 0,
      "elapsed_s": 0,
      "error": null,
      "alphas": []
    },
    {
      "molecule_id": "HSi+_singlet_Coov",
      "basis": "sto-3g",
      "status": "complete",
      "n_alphas": 10,
      "n_ok": 10,
      "n_fci_converged": 10,
      "n_spin_mismatch": 0,
      "elapsed_s": 0,
      "error": null,
      "alphas": []
    },
    {
      "molecule_id": "HeLi+_singlet_C1",
      "basis": "3-21g",
      "status": "complete",
      "n_alphas": 10,
      "n_ok": 10,
      "n_fci_converged": 10,
      "n_spin_mismatch": 0,
      "elapsed_s": 0,
      "error": null,
      "alphas": []
    },
    {
      "molecule_id": "HeLi+_singlet_C1",
      "basis": "sto-3g",
      "status": "complete",
      "n_alphas": 10,
      "n_ok": 10,
      "n_fci_converged": 10,
      "n_spin_mismatch": 0,
      "elapsed_s": 0,
      "error": null,
      "alphas": []
    },
    {
      "molecule_id": "He_singlet_Kh",
      "basis": "3-21g",
      "status": "complete",
      "n_alphas": 1,
      "n_ok": 1,
      "n_fci_converged": 1,
      "n_spin_mismatch": 0,
      "elapsed_s": 0,
      "error": null,
      "alphas": []
    },
    {
      "molecule_id": "He_singlet_Kh",
      "basis": "6-311g**",
      "status": "complete",
      "n_alphas": 1,
      "n_ok": 1,
      "n_fci_converged": 1,
      "n_spin_mismatch": 0,
      "elapsed_s": 0,
      "error": null,
      "alphas": []
    },
    {
      "molecule_id": "He_singlet_Kh",
      "basis": "6-31g**",
      "status": "complete",
      "n_alphas": 1,
      "n_ok": 1,
      "n_fci_converged": 1,
      "n_spin_mismatch": 0,
      "elapsed_s": 0,
      "error": null,
      "alphas": []
    },
    {
      "molecule_id": "He_singlet_Kh",
      "basis": "cc-pvdz",
      "status": "complete",
      "n_alphas": 1,
      "n_ok": 1,
      "n_fci_converged": 1,
      "n_spin_mismatch": 0,
      "elapsed_s": 0,
      "error": null,
      "alphas": []
    },
    {
      "molecule_id": "He_singlet_Kh",
      "basis": "sto-3g",
      "status": "complete",
      "n_alphas": 1,
      "n_ok": 1,
      "n_fci_converged": 1,
      "n_spin_mismatch": 0,
      "elapsed_s": 0,
      "error": null,
      "alphas": []
    },
    {
      "molecule_id": "Li+_singlet_Kh",
      "basis": "3-21g",
      "status": "complete",
      "n_alphas": 1,
      "n_ok": 1,
      "n_fci_converged": 1,
      "n_spin_mismatch": 0,
      "elapsed_s": 0,
      "error": null,
      "alphas": []
    },
    {
      "molecule_id": "Li+_singlet_Kh",
      "basis": "sto-3g",
      "status": "complete",
      "n_alphas": 1,
      "n_ok": 1,
      "n_fci_converged": 1,
      "n_spin_mismatch": 0,
      "elapsed_s": 0,
      "error": null,
      "alphas": []
    },
    {
      "molecule_id": "Li-_singlet_Kh",
      "basis": "3-21g",
      "status": "complete",
      "n_alphas": 1,
      "n_ok": 1,
      "n_fci_converged": 1,
      "n_spin_mismatch": 0,
      "elapsed_s": 0,
      "error": null,
      "alphas": []
    },
    {
      "molecule_id": "Li-_singlet_Kh",
      "basis": "sto-3g",
      "status": "complete",
      "n_alphas": 1,
      "n_ok": 1,
      "n_fci_converged": 1,
      "n_spin_mismatch": 0,
      "elapsed_s": 0,
      "error": null,
      "alphas": []
    },
    {
      "molecule_id": "Li2_singlet_Dooh",
      "basis": "sto-3g",
      "status": "complete",
      "n_alphas": 10,
      "n_ok": 10,
      "n_fci_converged": 10,
      "n_spin_mismatch": 0,
      "elapsed_s": 0,
      "error": null,
      "alphas": []
    },
    {
      "molecule_id": "LiNe+_singlet_C1",
      "basis": "sto-3g",
      "status": "complete",
      "n_alphas": 10,
      "n_ok": 10,
      "n_fci_converged": 10,
      "n_spin_mismatch": 0,
      "elapsed_s": 0,
      "error": null,
      "alphas": []
    },
    {
      "molecule_id": "LiO-_singlet_Coov",
      "basis": "sto-3g",
      "status": "complete",
      "n_alphas": 10,
      "n_ok": 10,
      "n_fci_converged": 10,
      "n_spin_mismatch": 0,
      "elapsed_s": 0,
      "error": null,
      "alphas": []
    },
    {
      "molecule_id": "Mg_singlet_Kh",
      "basis": "sto-3g",
      "status": "complete",
      "n_alphas": 1,
      "n_ok": 1,
      "n_fci_converged": 1,
      "n_spin_mismatch": 0,
      "elapsed_s": 0,
      "error": null,
      "alphas": []
    },
    {
      "molecule_id": "N2_singlet_Dooh",
      "basis": "sto-3g",
      "status": "complete",
      "n_alphas": 10,
      "n_ok": 10,
      "n_fci_converged": 10,
      "n_spin_mismatch": 0,
      "elapsed_s": 0,
      "error": null,
      "alphas": []
    },
    {
      "molecule_id": "NO+_singlet_Coov",
      "basis": "sto-3g",
      "status": "complete",
      "n_alphas": 10,
      "n_ok": 10,
      "n_fci_converged": 10,
      "n_spin_mismatch": 0,
      "elapsed_s": 0,
      "error": null,
      "alphas": []
    },
    {
      "molecule_id": "Na+_singlet_Kh",
      "basis": "sto-3g",
      "status": "complete",
      "n_alphas": 1,
      "n_ok": 1,
      "n_fci_converged": 1,
      "n_spin_mismatch": 0,
      "elapsed_s": 0,
      "error": null,
      "alphas": []
    },
    {
      "molecule_id": "Na-_singlet_Kh",
      "basis": "sto-3g",
      "status": "complete",
      "n_alphas": 1,
      "n_ok": 1,
      "n_fci_converged": 1,
      "n_spin_mismatch": 0,
      "elapsed_s": 0,
      "error": null,
      "alphas": []
    },
    {
      "molecule_id": "Ne2_singlet_Dooh",
      "basis": "sto-3g",
      "status": "complete",
      "n_alphas": 10,
      "n_ok": 10,
      "n_fci_converged": 10,
      "n_spin_mismatch": 0,
      "elapsed_s": 0,
      "error": null,
      "alphas": []
    },
    {
      "molecule_id": "Ne_singlet_Kh",
      "basis": "3-21g",
      "status": "complete",
      "n_alphas": 1,
      "n_ok": 1,
      "n_fci_converged": 1,
      "n_spin_mismatch": 0,
      "elapsed_s": 0,
      "error": null,
      "alphas": []
    },
    {
      "molecule_id": "Ne_singlet_Kh",
      "basis": "sto-3g",
      "status": "complete",
      "n_alphas": 1,
      "n_ok": 1,
      "n_fci_converged": 1,
      "n_spin_mismatch": 0,
      "elapsed_s": 0,
      "error": null,
      "alphas": []
    },
    {
      "molecule_id": "O2--_singlet_Dooh",
      "basis": "sto-3g",
      "status": "complete",
      "n_alphas": 10,
      "n_ok": 10,
      "n_fci_converged": 10,
      "n_spin_mismatch": 0,
      "elapsed_s": 0,
      "error": null,
      "alphas": []
    },
    {
      "molecule_id": "H2O2_singlet_C2v",
      "basis": "sto-3g",
      "status": "complete",
      "n_alphas": 10,
      "n_ok": 10,
      "n_fci_converged": 8,
      "n_spin_mismatch": 0,
      "elapsed_s": 0,
      "error": null,
      "alphas": []
    },
    {
      "molecule_id": "H10_singlet_Dooh",
      "basis": "sto-3g",
      "status": "complete",
      "n_alphas": 10,
      "n_ok": 10,
      "n_fci_converged": 10,
      "n_spin_mismatch": 0,
      "elapsed_s": 0,
      "error": null,
      "alphas": []
    },
    {
      "molecule_id": "H4_singlet_Dooh",
      "basis": "3-21g",
      "status": "complete",
      "n_alphas": 10,
      "n_ok": 10,
      "n_fci_converged": 10,
      "n_spin_mismatch": 0,
      "elapsed_s": 0,
      "error": null,
      "alphas": []
    },
    {
      "molecule_id": "H4_singlet_Dooh",
      "basis": "sto-3g",
      "status": "complete",
      "n_alphas": 10,
      "n_ok": 10,
      "n_fci_converged": 10,
      "n_spin_mismatch": 0,
      "elapsed_s": 0,
      "error": null,
      "alphas": []
    },
    {
      "molecule_id": "H6_singlet_Dooh",
      "basis": "3-21g",
      "status": "complete",
      "n_alphas": 10,
      "n_ok": 10,
      "n_fci_converged": 10,
      "n_spin_mismatch": 0,
      "elapsed_s": 0,
      "error": null,
      "alphas": []
    },
    {
      "molecule_id": "H6_singlet_Dooh",
      "basis": "sto-3g",
      "status": "complete",
      "n_alphas": 10,
      "n_ok": 10,
      "n_fci_converged": 10,
      "n_spin_mismatch": 0,
      "elapsed_s": 0,
      "error": null,
      "alphas": []
    },
    {
      "molecule_id": "H8_singlet_Dooh",
      "basis": "sto-3g",
      "status": "complete",
      "n_alphas": 10,
      "n_ok": 10,
      "n_fci_converged": 10,
      "n_spin_mismatch": 0,
      "elapsed_s": 0,
      "error": null,
      "alphas": []
    },
    {
      "molecule_id": "He2_singlet_Dooh",
      "basis": "3-21g",
      "status": "complete",
      "n_alphas": 10,
      "n_ok": 10,
      "n_fci_converged": 10,
      "n_spin_mismatch": 0,
      "elapsed_s": 0,
      "error": null,
      "alphas": []
    },
    {
      "molecule_id": "He2_singlet_Dooh",
      "basis": "6-311g**",
      "status": "complete",
      "n_alphas": 10,
      "n_ok": 10,
      "n_fci_converged": 10,
      "n_spin_mismatch": 0,
      "elapsed_s": 0,
      "error": null,
      "alphas": []
    },
    {
      "molecule_id": "He2_singlet_Dooh",
      "basis": "6-31g**",
      "status": "complete",
      "n_alphas": 10,
      "n_ok": 10,
      "n_fci_converged": 10,
      "n_spin_mismatch": 0,
      "elapsed_s": 0,
      "error": null,
      "alphas": []
    },
    {
      "molecule_id": "He2_singlet_Dooh",
      "basis": "cc-pvdz",
      "status": "complete",
      "n_alphas": 10,
      "n_ok": 10,
      "n_fci_converged": 10,
      "n_spin_mismatch": 0,
      "elapsed_s": 0,
      "error": null,
      "alphas": []
    },
    {
      "molecule_id": "He2_singlet_Dooh",
      "basis": "sto-3g",
      "status": "complete",
      "n_alphas": 10,
      "n_ok": 10,
      "n_fci_converged": 10,
      "n_spin_mismatch": 0,
      "elapsed_s": 0,
      "error": null,
      "alphas": []
    },
    {
      "molecule_id": "H3+_singlet_D3h",
      "basis": "3-21g",
      "status": "complete",
      "n_alphas": 10,
      "n_ok": 10,
      "n_fci_converged": 10,
      "n_spin_mismatch": 0,
      "elapsed_s": 0,
      "error": null,
      "alphas": []
    },
    {
      "molecule_id": "H3+_singlet_D3h",
      "basis": "sto-3g",
      "status": "complete",
      "n_alphas": 10,
      "n_ok": 10,
      "n_fci_converged": 10,
      "n_spin_mismatch": 0,
      "elapsed_s": 0,
      "error": null,
      "alphas": []
    },
    {
      "molecule_id": "H3N_singlet_Cs",
      "basis": "sto-3g",
      "status": "complete",
      "n_alphas": 10,
      "n_ok": 10,
      "n_fci_converged": 10,
      "n_spin_mismatch": 0,
      "elapsed_s": 0,
      "error": null,
      "alphas": []
    },
    {
      "molecule_id": "H3O+_singlet_C3v",
      "basis": "sto-3g",
      "status": "complete",
      "n_alphas": 10,
      "n_ok": 10,
      "n_fci_converged": 10,
      "n_spin_mismatch": 0,
      "elapsed_s": 0,
      "error": null,
      "alphas": []
    },
    {
      "molecule_id": "H4_singlet_D4h",
      "basis": "3-21g",
      "status": "complete",
      "n_alphas": 10,
      "n_ok": 10,
      "n_fci_converged": 10,
      "n_spin_mismatch": 0,
      "elapsed_s": 0,
      "error": null,
      "alphas": []
    },
    {
      "molecule_id": "H4_singlet_D4h",
      "basis": "sto-3g",
      "status": "complete",
      "n_alphas": 10,
      "n_ok": 10,
      "n_fci_converged": 10,
      "n_spin_mismatch": 0,
      "elapsed_s": 0,
      "error": null,
      "alphas": []
    },
    {
      "molecule_id": "HN_singlet_Coov",
      "basis": "3-21g",
      "status": "complete",
      "n_alphas": 10,
      "n_ok": 10,
      "n_fci_converged": 10,
      "n_spin_mismatch": 0,
      "elapsed_s": 0,
      "error": null,
      "alphas": []
    },
    {
      "molecule_id": "HN_singlet_Coov",
      "basis": "sto-3g",
      "status": "complete",
      "n_alphas": 10,
      "n_ok": 10,
      "n_fci_converged": 10,
      "n_spin_mismatch": 0,
      "elapsed_s": 0,
      "error": null,
      "alphas": []
    }
  ]
}